codingtoolkit/__init__.py
codingtoolkit/flags.py
module/__init__.py
module/flags.py
codingtoolkit-0.0.3.dist-info/METADATA
codingtoolkit-0.0.3.dist-info/WHEEL
codingtoolkit-0.0.3.dist-info/top_level.txt
codingtoolkit-0.0.3.dist-info/RECORD
