Metadata-Version: 2.1
Name: codingtoolkit
Version: 0.0.3
Summary: A coding toolkit for python
Home-page: UNKNOWN
Author: flyingreshin
Author-email: flyingreshin@gmail.com
License: UNKNOWN
Keywords: python,first package
Platform: UNKNOWN
Classifier: Development Status :: 3 - Alpha
Classifier: Intended Audience :: Education
Classifier: Programming Language :: Python :: 2
Classifier: Programming Language :: Python :: 3
Classifier: Operating System :: MacOS :: MacOS X
Classifier: Operating System :: Microsoft :: Windows
